odoo/addons/crowdfunding/README.rst
odoo/addons/crowdfunding/__init__.py
odoo/addons/crowdfunding/__manifest__.py
odoo/addons/crowdfunding/controllers/__init__.py
odoo/addons/crowdfunding/controllers/main.py
odoo/addons/crowdfunding/controllers/payment.py
odoo/addons/crowdfunding/data/product_product.xml
odoo/addons/crowdfunding/data/website_menu.xml
odoo/addons/crowdfunding/demo/crowdfunding_challenge.xml
odoo/addons/crowdfunding/i18n/crowdfunding.pot
odoo/addons/crowdfunding/i18n/it.po
odoo/addons/crowdfunding/models/__init__.py
odoo/addons/crowdfunding/models/account_move.py
odoo/addons/crowdfunding/models/crowdfunding_challenge.py
odoo/addons/crowdfunding/models/payment_transaction.py
odoo/addons/crowdfunding/models/res_company.py
odoo/addons/crowdfunding/models/res_config_settings.py
odoo/addons/crowdfunding/readme/CONFIGURE.md
odoo/addons/crowdfunding/readme/CONTRIBUTORS.md
odoo/addons/crowdfunding/readme/DESCRIPTION.md
odoo/addons/crowdfunding/readme/ROADMAP.md
odoo/addons/crowdfunding/readme/USAGE.md
odoo/addons/crowdfunding/security/crowdfunding_security.xml
odoo/addons/crowdfunding/security/ir.model.access.csv
odoo/addons/crowdfunding/static/description/icon.png
odoo/addons/crowdfunding/static/description/index.html
odoo/addons/crowdfunding/static/tests/tours/crowdfunding_frontend.js
odoo/addons/crowdfunding/templates/assets.xml
odoo/addons/crowdfunding/templates/crowdfunding_challenge.xml
odoo/addons/crowdfunding/templates/payment.xml
odoo/addons/crowdfunding/tests/__init__.py
odoo/addons/crowdfunding/tests/test_crowdfunding_frontend.py
odoo/addons/crowdfunding/views/account_move.xml
odoo/addons/crowdfunding/views/crowdfunding_challenge.xml
odoo/addons/crowdfunding/views/menu.xml
odoo/addons/crowdfunding/views/payment_transaction.xml
odoo/addons/crowdfunding/views/res_config_settings.xml
odoo/addons/crowdfunding/wizards/__init__.py
odoo/addons/crowdfunding/wizards/crowdfunding_invoicing_wizard.py
odoo14_addon_crowdfunding-14.0.1.3.0.dist-info/METADATA
odoo14_addon_crowdfunding-14.0.1.3.0.dist-info/WHEEL
odoo14_addon_crowdfunding-14.0.1.3.0.dist-info/top_level.txt
odoo14_addon_crowdfunding-14.0.1.3.0.dist-info/RECORD
