Metadata-Version: 2.1
Name: odoo14-addon-crowdfunding
Version: 14.0.1.3.0
Summary: Turn Odoo into a platform for crowdfunding
Home-page: https://github.com/OCA/crowdfunding
Author: Hunki Enterprises BV, Odoo Community Association (OCA)
Author-email: support@odoo-community.org
License: AGPL-3
Classifier: Programming Language :: Python
Classifier: Framework :: Odoo
Classifier: Framework :: Odoo :: 14.0
Classifier: License :: OSI Approved :: GNU Affero General Public License v3
Classifier: Development Status :: 3 - Alpha
Requires-Python: >=3.6
Requires-Dist: odoo14-addon-onchange-helper
Requires-Dist: odoo<14.1dev,>=14.0a
